poi_tracker/__init__.py
poi_tracker/cli.py
poi_tracker/exporters.py
poi_tracker/inventory.py
poi_tracker/utils.py
poi_tracker-0.0.1.dist-info/COPYING.md
poi_tracker-0.0.1.dist-info/METADATA
poi_tracker-0.0.1.dist-info/WHEEL
poi_tracker-0.0.1.dist-info/entry_points.txt
poi_tracker-0.0.1.dist-info/top_level.txt
poi_tracker-0.0.1.dist-info/RECORD
