Metadata-Version: 2.1
Name: poi-tracker
Version: 0.0.1
Summary: Tool for tracking packages of interest
Home-page: https://pagure.io/michel-slm/poi-tracker
Author: Michel Lind
Author-email: salimma@fedoraproject.org
License: GPLv2+
Classifier: Development Status :: 3 - Alpha
Classifier: Environment :: Console
Classifier: License :: OSI Approved :: GNU General Public License v2 or later (GPLv2+)
License-File: COPYING.md
Requires-Dist: click
Requires-Dist: email-validator
Requires-Dist: pydantic>=2.0.0
Requires-Dist: pyyaml
Provides-Extra: dev
Requires-Dist: black; extra == "dev"
Requires-Dist: build; extra == "dev"
Requires-Dist: pip-tools; extra == "dev"
Requires-Dist: pytest; extra == "dev"
Requires-Dist: pytest-cov; extra == "dev"
Provides-Extra: test
Requires-Dist: pytest; extra == "test"
